odoo/addons/stock_analytic/README.rst
odoo/addons/stock_analytic/__init__.py
odoo/addons/stock_analytic/__manifest__.py
odoo/addons/stock_analytic/i18n/ca.po
odoo/addons/stock_analytic/i18n/cs_CZ.po
odoo/addons/stock_analytic/i18n/de.po
odoo/addons/stock_analytic/i18n/el_GR.po
odoo/addons/stock_analytic/i18n/es.po
odoo/addons/stock_analytic/i18n/es_EC.po
odoo/addons/stock_analytic/i18n/es_MX.po
odoo/addons/stock_analytic/i18n/fi.po
odoo/addons/stock_analytic/i18n/fr.po
odoo/addons/stock_analytic/i18n/gl.po
odoo/addons/stock_analytic/i18n/gu_IN.po
odoo/addons/stock_analytic/i18n/hi_IN.po
odoo/addons/stock_analytic/i18n/hr.po
odoo/addons/stock_analytic/i18n/hr_HR.po
odoo/addons/stock_analytic/i18n/hu.po
odoo/addons/stock_analytic/i18n/it.po
odoo/addons/stock_analytic/i18n/nl.po
odoo/addons/stock_analytic/i18n/pl.po
odoo/addons/stock_analytic/i18n/pt.po
odoo/addons/stock_analytic/i18n/pt_BR.po
odoo/addons/stock_analytic/i18n/pt_PT.po
odoo/addons/stock_analytic/i18n/ro.po
odoo/addons/stock_analytic/i18n/sk_SK.po
odoo/addons/stock_analytic/i18n/sl.po
odoo/addons/stock_analytic/i18n/stock_analytic.pot
odoo/addons/stock_analytic/i18n/tr.po
odoo/addons/stock_analytic/i18n/tr_TR.po
odoo/addons/stock_analytic/i18n/vi_VN.po
odoo/addons/stock_analytic/i18n/zh_CN.po
odoo/addons/stock_analytic/migrations/14.0.2.0.0/pre-migrate.py
odoo/addons/stock_analytic/models/__init__.py
odoo/addons/stock_analytic/models/product_product.py
odoo/addons/stock_analytic/models/stock.py
odoo/addons/stock_analytic/models/stock_scrap.py
odoo/addons/stock_analytic/readme/CONTRIBUTORS.rst
odoo/addons/stock_analytic/readme/DESCRIPTION.rst
odoo/addons/stock_analytic/readme/USAGE.rst
odoo/addons/stock_analytic/static/description/icon.png
odoo/addons/stock_analytic/static/description/index.html
odoo/addons/stock_analytic/tests/__init__.py
odoo/addons/stock_analytic/tests/test_stock_picking.py
odoo/addons/stock_analytic/tests/test_stock_scrap.py
odoo/addons/stock_analytic/views/stock_move_line.xml
odoo14_addon_stock_analytic-14.0.2.1.2.dist-info/METADATA
odoo14_addon_stock_analytic-14.0.2.1.2.dist-info/WHEEL
odoo14_addon_stock_analytic-14.0.2.1.2.dist-info/top_level.txt
odoo14_addon_stock_analytic-14.0.2.1.2.dist-info/RECORD
