Metadata-Version: 2.1
Name: odoo14-addon-stock-analytic
Version: 14.0.2.1.2
Summary: Adds an analytic account and analytic tags in stock move
Home-page: https://github.com/OCA/account-analytic
Author: Julius Network Solutions, ClearCorp, OpenSynergy Indonesia, Hibou Corp., Odoo Community Association (OCA)
Author-email: support@odoo-community.org
License: AGPL-3
Platform: UNKNOWN
Classifier: Programming Language :: Python
Classifier: Framework :: Odoo
Classifier: Framework :: Odoo :: 14.0
Classifier: License :: OSI Approved :: GNU Affero General Public License v3
Requires-Python: >=3.6
Requires-Dist: odoo <14.1dev,>=14.0a
